{
	"name": "studio",
	"progressCollectibles": 3,
	"start": {
		"x": 20,
		"y": 40
	},
	"exit": {
		"x": 10,
		"y": 483
	},
	"collectibles": [
		{
			"x": 135,
			"y": 77,
			"type": "coin"
		},
		{
			"x": 63,
			"y": 46,
			"type": "coin"
		},
		{
			"x": 85,
			"y": 46,
			"type": "coin"
		},
		{
			"x": 96,
			"y": 183,
			"type": "coin"
		},
		{
			"x": 58,
			"y": 195,
			"type": "coin"
		},
		{
			"x": 26,
			"y": 149,
			"type": "guitar-purple"
		},
		{
			"x": 62,
			"y": 355,
			"type": "speakers"
		},
		{
			"x": 31,
			"y": 400,
			"type": "coin"
		},
		{
			"x": 55,
			"y": 401,
			"type": "coin"
		},
		{
			"x": 79,
			"y": 402,
			"type": "coin"
		},
		{
			"x": 141,
			"y": 185,
			"type": "mic"
		}
	],
	"objects": [
		{
			"x": 108,
			"y": 6,
			"type": "static-bucket-red"
		},
		{
			"x": 116,
			"y": 6,
			"type": "static-bucket-blue"
		},
		{
			"x": 67,
			"y": 106,
			"type": "crate"
		},
		{
			"type": "water",
			"x": 24,
			"y": 236
		},
		{
			"type": "pipe-damage",
			"x": 67,
			"y": 295
		},
		{
			"type": "bucket-stack",
			"x": 140,
			"y": 395
		}
	],
	"props": [
		{
			"x": 13,
			"y": 85,
			"type": "hang-light"
		},
		{
			"x": 73,
			"y": 85,
			"type": "hang-light"
		},
		{
			"type": "beams-triple",
			"x": 32,
			"y": 6
		},
		{
			"type": "beams-double",
			"x": 5,
			"y": 103
		},
		{
			"type": "beams",
			"x": 127,
			"y": -5
		},
		{
			"type": "beams",
			"x": 127,
			"y": 30
		},
		{
			"type": "beams",
			"x": 127,
			"y": 65
		},
		{
			"type": "breaker-box",
			"x": 90,
			"y": 263
		},
		{
			"type": "breaker-box-wire",
			"x": 110,
			"y": 255
		},
		{
			"type": "wire",
			"x": 106,
			"y": 241
		},
		{
			"type": "pipe",
			"x": 0,
			"y": 295
		},
		{
			"type": "board",
			"x": 15,
			"y": 525
		},
		{
			"type": "studio-desk",
			"x": 32,
			"y": 473
		},
		{
			"type": "mic-stand",
			"x": 5,
			"y": 475
		},
		{
			"type": "guitars",
			"x": 72,
			"y": 530
		},
		{
			"type": "nm-logo",
			"x": 119,
			"y": 487
		}
	],
	"platforms": [
		{
			"x": 0,
			"y": 6,
			"segments": 10,
			"type": "wood-floor"
		},
		{
			"x": 31,
			"y": 41,
			"segments": 3
		},
		{
			"x": 127,
			"y": 30
		},
		{
			"x": 127,
			"y": 65
		},
		{
			"x": 127,
			"y": 100
		},
		{
			"x": -1,
			"y": 106,
			"segments": 4,
			"type": "wood-floor"
		},
		{
			"x": 5,
			"y": 128,
			"segments": 1
		},
		{
			"x": 28,
			"y": 128,
			"segments": 1
		},
		{
			"x": 130,
			"y": 165,
			"segments": 2,
			"type": "wood-floor"
		},
		{
			"x": -16,
			"y": 201,
			"segments": 2,
			"type": "factory"
		},
		{
			"x": 88,
			"y": 177,
			"segments": 1,
			"type": "factory"
		},
		{
			"x": 50,
			"y": 189,
			"segments": 1,
			"type": "factory"
		},
		{
			"x": 0,
			"y": 241,
			"segments": 10,
			"type": "wood-floor"
		},
		{
			"x": -3,
			"y": 341,
			"segments": 1,
			"type": "factory"
		},
		{
			"x": 56,
			"y": 341,
			"segments": 2,
			"type": "factory"
		},
		{
			"x": 139,
			"y": 341,
			"segments": 2,
			"type": "factory"
		},
		{
			"x": 0,
			"y": 391,
			"segments": 4,
			"type": "wood-floor",
			"angled": "up"
		},
		{
			"x": 96,
			"y": 395,
			"segments": 3,
			"type": "wood-floor"
		},
		{
			"x": 0,
			"y": 475,
			"segments": 10,
			"type": "carpet"
		},
		{
			"x": 0,
			"y": 525,
			"segments": 10,
			"type": "carpet"
		}
	],
	"ladders": [
		{
			"x": 37,
			"y": 41,
			"segments": 13
		},
		{
			"x": 140,
			"y": 100,
			"segments": 13
		},
		{
			"x": 8,
			"y": 201,
			"segments": 8
		},
		{
			"x": 144,
			"y": 241,
			"segments": 20
		},
		{
			"x": 6,
			"y": 341,
			"segments": 10
		},
		{
			"x": 128,
			"y": 395,
			"segments": 16
		}
	]
}
